pyproject.toml
substantial/__init__.py
substantial/agent.py
substantial/backends/backend.py
substantial/backends/fs.py
substantial/backends/redis.py
substantial/conductor.py
substantial/filters.py
substantial/protos/__init__.py
substantial/protos/events/__init__.py
substantial/protos/metadata/__init__.py
substantial/types.py
substantial/workflows/__init__.py
substantial/workflows/context.py
substantial/workflows/parser.py
substantial/workflows/run.py
substantial/workflows/workflow.py
substantial-0.1.0.dist-info/LICENSE
substantial-0.1.0.dist-info/METADATA
substantial-0.1.0.dist-info/WHEEL
substantial-0.1.0.dist-info/RECORD
