Metadata-Version: 2.1
Name: substantial
Version: 0.1.0
Summary: Brokerless durable execution for Python.
License: MPL-2.0
Keywords: durable,execution,redis,s3,filesystem
Requires-Python: >=3.11,<4.0
Classifier: License :: OSI Approved
Classifier: Programming Language :: Python
Classifier: Programming Language :: Python :: 3
Classifier: Programming Language :: Python :: 3.11
Classifier: Programming Language :: Python :: 3.12
Classifier: Topic :: Software Development :: Libraries :: Python Modules
Requires-Dist: aioprocessing[dill] (==2.0.1)
Requires-Dist: asyncio (>=3.4.3,<4.0.0)
Requires-Dist: betterproto[compiler] (==2.0.0b7)
Requires-Dist: orjson (>=3.10.13,<4.0.0)
Requires-Dist: pydantic (>=2.10.4,<3.0.0)
Requires-Dist: redis (>=5.2.1,<6.0.0)
Requires-Dist: uvloop (>=0.21.0,<0.22.0)
